<?xml version="1.0" encoding="utf-8" ?>
<dwsync>
<file name="login-submit.cfm" server="www.prefiniti.com/prefiniti15/" local="129534370311235081" remote="129534370200000000" />
<file name="Prefiniti.cfm" server="www.prefiniti.com/prefiniti15/" local="129535987188224068" remote="129535987200000000" />
<file name="webwareConfigLoad.cfm" server="www.prefiniti.com/prefiniti15/" local="129514225273524164" remote="129514420800000000" />
<file name="scriptIncludes.cfm" server="www.prefiniti.com/prefiniti15/" local="129534354884302711" remote="129534354600000000" />
<file name="siteSelectSubmit2.cfm" server="www.prefiniti.com/prefiniti15/" local="129526572485554800" remote="129526572000000000" />
<file name="logoff.cfm" server="www.prefiniti.com/prefiniti15/" local="129522768303611867" remote="129522768000000000" />
<file name="desktop_login.cfm" server="www.prefiniti.com/prefiniti15/" local="129514428373890840" remote="129514428000000000" />
<file name="Res.cfc" server="www.prefiniti.com/prefiniti15/" local="129522115587398635" remote="129522115200000000" />
<file name="headBar.cfm" server="www.prefiniti.com/prefiniti15/" local="129178584000000000" remote="129178584000000000" />
<file name="migration_scripts.cfm" server="www.prefiniti.com/prefiniti15/" local="128451096000000000" remote="128451096000000000" />
<file name="jumploader_z.jar" server="www.prefiniti.com/prefiniti15/" local="129520433537780900" remote="129520446600000000" />
<file name="Prefiniti.cfc" server="www.prefiniti.com/prefiniti15/" local="129521043907682062" remote="129521043600000000" />
<file name="prefiniti.ini" server="www.prefiniti.com/prefiniti15/" local="129534369709950690" remote="129534369600000000" />
<file name="ORMS.cfm" server="www.prefiniti.com/prefiniti15/" local="129522114277923738" remote="129522114000000000" />
<file name="soundManagerDiv.cfm" server="www.prefiniti.com/prefiniti15/" local="128614392000000000" remote="128614392000000000" />
<file name="soundmanager.js" server="www.prefiniti.com/prefiniti15/" local="127412568000000000" remote="127412568000000000" />
<file name="siteSelect.cfm" server="www.prefiniti.com/prefiniti15/" local="129526342040404091" remote="129526341600000000" />
<file name="bad_site_permissions.cfm" server="www.prefiniti.com/prefiniti15/" local="129526345597847565" remote="129526345200000000" />
<file name="Application.cfm" server="www.prefiniti.com/prefiniti15/" local="129535988514789943" remote="129535988400000000" />
<file name="styleConfig.cfm" server="www.prefiniti.com/prefiniti15/" local="129534357895714954" remote="129534357600000000" />
<file name="browserDetection.cfm" server="www.prefiniti.com/prefiniti15/" local="128614392000000000" remote="128614392000000000" />
<file name="default.cfm" server="www.prefiniti.com/prefiniti15/" local="129534368846111281" remote="129534368400000000" />
</dwsync>